[
  {
    "id": "hilihoru",
    "name": "Hilihoru",
    "district": "amandraya"
  },
  {
    "id": "hilimbulawa",
    "name": "Hilimbulawa",
    "district": "amandraya"
  },
  {
    "id": "sifaoroasi",
    "name": "Sifaoroasi",
    "district": "amandraya"
  },
  {
    "id": "sisobahili",
    "name": "Sisobahili",
    "district": "amandraya"
  },
  {
    "id": "tuindrao",
    "name": "Tuindrao",
    "district": "amandraya"
  },
  {
    "id": "hilimbowo",
    "name": "Hilimbowo",
    "district": "amandraya"
  },
  {
    "id": "lolozaria",
    "name": "Lolozaria",
    "district": "amandraya"
  },
  {
    "id": "lolomoyo",
    "name": "Lolomoyo",
    "district": "amandraya"
  },
  {
    "id": "hilifadolo",
    "name": "Hilifadolo",
    "district": "amandraya"
  },
  {
    "id": "orahili-eho",
    "name": "Orahili Eho",
    "district": "amandraya"
  },
  {
    "id": "sirofi",
    "name": "Sirofi",
    "district": "amandraya"
  },
  {
    "id": "hilisaloo",
    "name": "Hilisaloo",
    "district": "amandraya"
  },
  {
    "id": "loloabolo",
    "name": "Loloabolo",
    "district": "amandraya"
  },
  {
    "id": "mohili",
    "name": "Mohili",
    "district": "amandraya"
  },
  {
    "id": "hilindraso",
    "name": "Hilindraso",
    "district": "amandraya"
  },
  {
    "id": "hilimaera",
    "name": "Hilimaera",
    "district": "amandraya"
  },
  {
    "id": "amandraya",
    "name": "Amandraya",
    "district": "amandraya"
  },
  {
    "id": "sinar-inoo",
    "name": "Sinar Inoo",
    "district": "amandraya"
  },
  {
    "id": "tuindrao-1",
    "name": "Tuindrao 1",
    "district": "amandraya"
  },
  {
    "id": "tuhemberua",
    "name": "Tuhemberua",
    "district": "amandraya"
  },
  {
    "id": "boholu",
    "name": "Boholu",
    "district": "amandraya"
  }
]