[
  {
    "id": "nawa-sawanawa",
    "name": "Nawa / Sawanawa",
    "district": "arso"
  },
  {
    "id": "workwana",
    "name": "Workwana",
    "district": "arso"
  },
  {
    "id": "upt-pir-iii-bagia",
    "name": "Upt Pir Iii / Bagia",
    "district": "arso"
  },
  {
    "id": "ubiyau",
    "name": "Ubiyau",
    "district": "arso"
  },
  {
    "id": "upt-pir-ii-yamta",
    "name": "Upt Pir Ii / Yamta",
    "district": "arso"
  },
  {
    "id": "arso-kota",
    "name": "Arso Kota",
    "district": "arso"
  },
  {
    "id": "upt-pir-i-yanamaa",
    "name": "Upt Pir I / Yanamaa",
    "district": "arso"
  },
  {
    "id": "upt-arso-ii-yuwanain",
    "name": "Upt Arso Ii / Yuwanain",
    "district": "arso"
  },
  {
    "id": "asyaman",
    "name": "Asyaman",
    "district": "arso"
  },
  {
    "id": "sawabum",
    "name": "Sawabum",
    "district": "arso"
  },
  {
    "id": "bate-bibiosi",
    "name": "Bate / Bibiosi",
    "district": "arso"
  }
]