[
  {
    "id": "koto-benai",
    "name": "Koto Benai",
    "district": "benai"
  },
  {
    "id": "talontam",
    "name": "Talontam",
    "district": "benai"
  },
  {
    "id": "banjar-benai",
    "name": "Banjar Benai",
    "district": "benai"
  },
  {
    "id": "gunung-kesiangan",
    "name": "Gunung Kesiangan",
    "district": "benai"
  },
  {
    "id": "banjar-lopak",
    "name": "Banjar Lopak",
    "district": "benai"
  },
  {
    "id": "pulau-kalimanting",
    "name": "Pulau Kalimanting",
    "district": "benai"
  },
  {
    "id": "tanjung",
    "name": "Tanjung",
    "district": "benai"
  },
  {
    "id": "pulau-ingu",
    "name": "Pulau Ingu",
    "district": "benai"
  },
  {
    "id": "simandolak",
    "name": "Simandolak",
    "district": "benai"
  },
  {
    "id": "tebing-tinggi",
    "name": "Tebing Tinggi",
    "district": "benai"
  },
  {
    "id": "pulau-lancang",
    "name": "Pulau Lancang",
    "district": "benai"
  },
  {
    "id": "pulau-tongah",
    "name": "Pulau Tongah",
    "district": "benai"
  },
  {
    "id": "ujung-tanjung",
    "name": "Ujung Tanjung",
    "district": "benai"
  },
  {
    "id": "siberakun",
    "name": "Siberakun",
    "district": "benai"
  },
  {
    "id": "benai",
    "name": "Benai",
    "district": "benai"
  },
  {
    "id": "benai-kecil",
    "name": "Benai Kecil",
    "district": "benai"
  }
]