[
  {
    "id": "lundo",
    "name": "Lundo",
    "district": "benjeng"
  },
  {
    "id": "balongtunjung",
    "name": "Balongtunjung",
    "district": "benjeng"
  },
  {
    "id": "balongmojo",
    "name": "Balongmojo",
    "district": "benjeng"
  },
  {
    "id": "bulangkulon",
    "name": "Bulangkulon",
    "district": "benjeng"
  },
  {
    "id": "sedapurklagen",
    "name": "Sedapurklagen",
    "district": "benjeng"
  },
  {
    "id": "deliksumber",
    "name": "Deliksumber",
    "district": "benjeng"
  },
  {
    "id": "munggugianti",
    "name": "Munggugianti",
    "district": "benjeng"
  },
  {
    "id": "bengkelolor",
    "name": "Bengkelolor",
    "district": "benjeng"
  },
  {
    "id": "gluranploso",
    "name": "Gluranploso",
    "district": "benjeng"
  },
  {
    "id": "bulurejo",
    "name": "Bulurejo",
    "district": "benjeng"
  },
  {
    "id": "dermo",
    "name": "Dermo",
    "district": "benjeng"
  },
  {
    "id": "kedungsekar",
    "name": "Kedungsekar",
    "district": "benjeng"
  },
  {
    "id": "klampok",
    "name": "Klampok",
    "district": "benjeng"
  },
  {
    "id": "sirnoboyo",
    "name": "Sirnoboyo",
    "district": "benjeng"
  },
  {
    "id": "kalipadang",
    "name": "Kalipadang",
    "district": "benjeng"
  },
  {
    "id": "karangankidul",
    "name": "Karangankidul",
    "district": "benjeng"
  },
  {
    "id": "munggugebang",
    "name": "Munggugebang",
    "district": "benjeng"
  },
  {
    "id": "banter",
    "name": "Banter",
    "district": "benjeng"
  },
  {
    "id": "metatu",
    "name": "Metatu",
    "district": "benjeng"
  },
  {
    "id": "jogodalu",
    "name": "Jogodalu",
    "district": "benjeng"
  },
  {
    "id": "punduttrate",
    "name": "Punduttrate",
    "district": "benjeng"
  },
  {
    "id": "jatirembe",
    "name": "Jatirembe",
    "district": "benjeng"
  }
]