[
  {
    "id": "ciampea-udik",
    "name": "Ciampea Udik",
    "district": "ciampea"
  },
  {
    "id": "cinangka",
    "name": "Cinangka",
    "district": "ciampea"
  },
  {
    "id": "cibuntu",
    "name": "Cibuntu",
    "district": "ciampea"
  },
  {
    "id": "cicadas",
    "name": "Cicadas",
    "district": "ciampea"
  },
  {
    "id": "tegal-waru",
    "name": "Tegal Waru",
    "district": "ciampea"
  },
  {
    "id": "bojong-jengkol",
    "name": "Bojong Jengkol",
    "district": "ciampea"
  },
  {
    "id": "cihideung-udik",
    "name": "Cihideung Udik",
    "district": "ciampea"
  },
  {
    "id": "cihideung-ilir",
    "name": "Cihideung Ilir",
    "district": "ciampea"
  },
  {
    "id": "cibanteng",
    "name": "Cibanteng",
    "district": "ciampea"
  },
  {
    "id": "bojong-rangkas",
    "name": "Bojong Rangkas",
    "district": "ciampea"
  },
  {
    "id": "cibadak",
    "name": "Cibadak",
    "district": "ciampea"
  },
  {
    "id": "ciampea",
    "name": "Ciampea",
    "district": "ciampea"
  }
]