[
  {
    "id": "sukajadi",
    "name": "Sukajadi",
    "district": "cibaliung"
  },
  {
    "id": "sudimanik",
    "name": "Sudimanik",
    "district": "cibaliung"
  },
  {
    "id": "sorongan",
    "name": "Sorongan",
    "district": "cibaliung"
  },
  {
    "id": "cihanjuang",
    "name": "Cihanjuang",
    "district": "cibaliung"
  },
  {
    "id": "cibingbin",
    "name": "Cibingbin",
    "district": "cibaliung"
  },
  {
    "id": "cibaliung",
    "name": "Cibaliung",
    "district": "cibaliung"
  },
  {
    "id": "mahendra",
    "name": "Mahendra",
    "district": "cibaliung"
  }
]