[
  {
    "id": "tumpakrejo",
    "name": "Tumpakrejo",
    "district": "gedangan"
  },
  {
    "id": "sindurejo",
    "name": "Sindurejo",
    "district": "gedangan"
  },
  {
    "id": "gajahrejo",
    "name": "Gajahrejo",
    "district": "gedangan"
  },
  {
    "id": "sidodadi",
    "name": "Sidodadi",
    "district": "gedangan"
  },
  {
    "id": "gedangan",
    "name": "Gedangan",
    "district": "gedangan"
  },
  {
    "id": "segaran",
    "name": "Segaran",
    "district": "gedangan"
  },
  {
    "id": "sumberejo",
    "name": "Sumberejo",
    "district": "gedangan"
  },
  {
    "id": "girimulyo",
    "name": "Girimulyo",
    "district": "gedangan"
  },
  {
    "id": "ganting",
    "name": "Ganting",
    "district": "gedangan"
  },
  {
    "id": "karangbong",
    "name": "Karangbong",
    "district": "gedangan"
  },
  {
    "id": "kragan",
    "name": "Kragan",
    "district": "gedangan"
  },
  {
    "id": "sruni",
    "name": "Sruni",
    "district": "gedangan"
  },
  {
    "id": "keboananom",
    "name": "Keboananom",
    "district": "gedangan"
  },
  {
    "id": "keboansikep",
    "name": "Keboansikep",
    "district": "gedangan"
  },
  {
    "id": "gedangan",
    "name": "Gedangan",
    "district": "gedangan"
  },
  {
    "id": "ketajen",
    "name": "Ketajen",
    "district": "gedangan"
  },
  {
    "id": "wedi",
    "name": "Wedi",
    "district": "gedangan"
  },
  {
    "id": "semambung",
    "name": "Semambung",
    "district": "gedangan"
  },
  {
    "id": "sawotratap",
    "name": "Sawotratap",
    "district": "gedangan"
  },
  {
    "id": "bangah",
    "name": "Bangah",
    "district": "gedangan"
  }
]