[
  {
    "id": "lumban-rau-barat",
    "name": "Lumban Rau Barat",
    "district": "habinsaran"
  },
  {
    "id": "lumban-rau-selatan",
    "name": "Lumban Rau Selatan",
    "district": "habinsaran"
  },
  {
    "id": "parsoburan-tengah",
    "name": "Parsoburan Tengah",
    "district": "habinsaran"
  },
  {
    "id": "parsoburan-barat",
    "name": "Parsoburan Barat",
    "district": "habinsaran"
  },
  {
    "id": "lumban-balik",
    "name": "Lumban Balik",
    "district": "habinsaran"
  },
  {
    "id": "lumban-pinasa",
    "name": "Lumban Pinasa",
    "district": "habinsaran"
  },
  {
    "id": "panamparan",
    "name": "Panamparan",
    "district": "habinsaran"
  },
  {
    "id": "lumban-ruhap",
    "name": "Lumban Ruhap",
    "district": "habinsaran"
  },
  {
    "id": "lumban-pea",
    "name": "Lumban Pea",
    "district": "habinsaran"
  },
  {
    "id": "hitetano",
    "name": "Hitetano",
    "district": "habinsaran"
  },
  {
    "id": "lobu-hole",
    "name": "Lobu Hole",
    "district": "habinsaran"
  },
  {
    "id": "batu-nabolon",
    "name": "Batu Nabolon",
    "district": "habinsaran"
  },
  {
    "id": "lumban-gaol",
    "name": "Lumban Gaol",
    "district": "habinsaran"
  },
  {
    "id": "tornagodang",
    "name": "Tornagodang",
    "district": "habinsaran"
  },
  {
    "id": "taonmarisi",
    "name": "Taonmarisi",
    "district": "habinsaran"
  },
  {
    "id": "pagar-batu",
    "name": "Pagar Batu",
    "district": "habinsaran"
  },
  {
    "id": "sibuntuon",
    "name": "Sibuntuon",
    "district": "habinsaran"
  },
  {
    "id": "aek-ulok",
    "name": "Aek Ulok",
    "district": "habinsaran"
  },
  {
    "id": "pangujungan",
    "name": "Pangujungan",
    "district": "habinsaran"
  },
  {
    "id": "lumban-pinasa-saroha",
    "name": "Lumban Pinasa Saroha",
    "district": "habinsaran"
  },
  {
    "id": "lumban-lintong",
    "name": "Lumban Lintong",
    "district": "habinsaran"
  },
  {
    "id": "pararungan",
    "name": "Pararungan",
    "district": "habinsaran"
  }
]