[
  {
    "id": "tandam-hulu-dua",
    "name": "Tandam Hulu Dua",
    "district": "hamparan-perak"
  },
  {
    "id": "kampung-tandam-hulu-satu",
    "name": "Kampung Tandam Hulu Satu",
    "district": "hamparan-perak"
  },
  {
    "id": "paya-bakung",
    "name": "Paya Bakung",
    "district": "hamparan-perak"
  },
  {
    "id": "klambir-lima-kampung",
    "name": "Klambir Lima Kampung",
    "district": "hamparan-perak"
  },
  {
    "id": "klambir-lima-kebon",
    "name": "Klambir Lima Kebon",
    "district": "hamparan-perak"
  },
  {
    "id": "klumpang-kebon",
    "name": "Klumpang Kebon",
    "district": "hamparan-perak"
  },
  {
    "id": "klumpang-kampung",
    "name": "Klumpang Kampung",
    "district": "hamparan-perak"
  },
  {
    "id": "sialang-muda",
    "name": "Sialang Muda",
    "district": "hamparan-perak"
  },
  {
    "id": "bulu-cina",
    "name": "Bulu Cina",
    "district": "hamparan-perak"
  },
  {
    "id": "tandam-hilir-satu",
    "name": "Tandam Hilir Satu",
    "district": "hamparan-perak"
  },
  {
    "id": "tandam-hilir-dua",
    "name": "Tandam Hilir Dua",
    "district": "hamparan-perak"
  },
  {
    "id": "kota-datar",
    "name": "Kota Datar",
    "district": "hamparan-perak"
  },
  {
    "id": "kota-rantang",
    "name": "Kota Rantang",
    "district": "hamparan-perak"
  },
  {
    "id": "kampung-lama",
    "name": "Kampung Lama",
    "district": "hamparan-perak"
  },
  {
    "id": "klambir",
    "name": "Klambir",
    "district": "hamparan-perak"
  },
  {
    "id": "kampung-selemak",
    "name": "Kampung Selemak",
    "district": "hamparan-perak"
  },
  {
    "id": "hamparan-perak",
    "name": "Hamparan Perak",
    "district": "hamparan-perak"
  },
  {
    "id": "sungai-baharu",
    "name": "Sungai Baharu",
    "district": "hamparan-perak"
  },
  {
    "id": "paluh-manan",
    "name": "Paluh Manan",
    "district": "hamparan-perak"
  },
  {
    "id": "paluh-kurau",
    "name": "Paluh Kurau",
    "district": "hamparan-perak"
  }
]