[
  {
    "id": "panggreh",
    "name": "Panggreh",
    "district": "jabon"
  },
  {
    "id": "trompoasri",
    "name": "Trompoasri",
    "district": "jabon"
  },
  {
    "id": "kedungrejo",
    "name": "Kedungrejo",
    "district": "jabon"
  },
  {
    "id": "kedungpandan",
    "name": "Kedungpandan",
    "district": "jabon"
  },
  {
    "id": "semambung",
    "name": "Semambung",
    "district": "jabon"
  },
  {
    "id": "kupang",
    "name": "Kupang",
    "district": "jabon"
  },
  {
    "id": "tambak-kalisogo",
    "name": "Tambak Kalisogo",
    "district": "jabon"
  },
  {
    "id": "balongtani",
    "name": "Balongtani",
    "district": "jabon"
  },
  {
    "id": "jemirahan",
    "name": "Jemirahan",
    "district": "jabon"
  },
  {
    "id": "dukuhsari",
    "name": "Dukuhsari",
    "district": "jabon"
  },
  {
    "id": "kedungcangkring",
    "name": "Kedungcangkring",
    "district": "jabon"
  },
  {
    "id": "pejarakan",
    "name": "Pejarakan",
    "district": "jabon"
  },
  {
    "id": "besuki",
    "name": "Besuki",
    "district": "jabon"
  },
  {
    "id": "keboguyang",
    "name": "Keboguyang",
    "district": "jabon"
  },
  {
    "id": "permisan",
    "name": "Permisan",
    "district": "jabon"
  }
]