[
  {
    "id": "mandalamekar",
    "name": "Mandalamekar",
    "district": "jatiwaras"
  },
  {
    "id": "kersagalih",
    "name": "Kersagalih",
    "district": "jatiwaras"
  },
  {
    "id": "ciwarak",
    "name": "Ciwarak",
    "district": "jatiwaras"
  },
  {
    "id": "jatiwaras",
    "name": "Jatiwaras",
    "district": "jatiwaras"
  },
  {
    "id": "papayan",
    "name": "Papayan",
    "district": "jatiwaras"
  },
  {
    "id": "neglasari",
    "name": "Neglasari",
    "district": "jatiwaras"
  },
  {
    "id": "kaputihan",
    "name": "Kaputihan",
    "district": "jatiwaras"
  },
  {
    "id": "setiawangi",
    "name": "Setiawangi",
    "district": "jatiwaras"
  },
  {
    "id": "sukakerta",
    "name": "Sukakerta",
    "district": "jatiwaras"
  },
  {
    "id": "kertarahayu",
    "name": "Kertarahayu",
    "district": "jatiwaras"
  },
  {
    "id": "mandala-hurip",
    "name": "Mandala Hurip",
    "district": "jatiwaras"
  }
]