[
  {
    "id": "tolo",
    "name": "Tolo",
    "district": "kelara"
  },
  {
    "id": "tolo-barat",
    "name": "Tolo Barat",
    "district": "kelara"
  },
  {
    "id": "tolo-selatan",
    "name": "Tolo Selatan",
    "district": "kelara"
  },
  {
    "id": "bontolebang",
    "name": "Bontolebang",
    "district": "kelara"
  },
  {
    "id": "samataring",
    "name": "Samataring",
    "district": "kelara"
  },
  {
    "id": "bonto-nompo",
    "name": "Bonto Nompo",
    "district": "kelara"
  },
  {
    "id": "gantarang",
    "name": "Gantarang",
    "district": "kelara"
  },
  {
    "id": "tombo-tombolo",
    "name": "Tombo-Tombolo",
    "district": "kelara"
  },
  {
    "id": "tolo-timur",
    "name": "Tolo Timur",
    "district": "kelara"
  },
  {
    "id": "tolo-utara",
    "name": "Tolo Utara",
    "district": "kelara"
  }
]