[
  {
    "id": "batuah",
    "name": "Batuah",
    "district": "loa-janan"
  },
  {
    "id": "tani-bakti",
    "name": "Tani Bakti",
    "district": "loa-janan"
  },
  {
    "id": "purwajaya",
    "name": "Purwajaya",
    "district": "loa-janan"
  },
  {
    "id": "loa-janan-ulu",
    "name": "Loa Janan Ulu",
    "district": "loa-janan"
  },
  {
    "id": "loa-duri-ulu",
    "name": "Loa Duri Ulu",
    "district": "loa-janan"
  },
  {
    "id": "bakungan",
    "name": "Bakungan",
    "district": "loa-janan"
  },
  {
    "id": "loa-duri-ilir",
    "name": "Loa Duri Ilir",
    "district": "loa-janan"
  },
  {
    "id": "tani-harapan",
    "name": "Tani Harapan",
    "district": "loa-janan"
  }
]