[
  {
    "id": "auki",
    "name": "Auki",
    "district": "padaido"
  },
  {
    "id": "wundi",
    "name": "Wundi",
    "district": "padaido"
  },
  {
    "id": "nusi-babaruk",
    "name": "Nusi Babaruk",
    "district": "padaido"
  },
  {
    "id": "nusi",
    "name": "Nusi",
    "district": "padaido"
  },
  {
    "id": "pai",
    "name": "Pai",
    "district": "padaido"
  },
  {
    "id": "sandidori",
    "name": "Sandidori",
    "district": "padaido"
  },
  {
    "id": "sorina",
    "name": "Sorina",
    "district": "padaido"
  },
  {
    "id": "inbeyomi",
    "name": "Inbeyomi",
    "district": "padaido"
  },
  {
    "id": "kanai",
    "name": "Kanai",
    "district": "padaido"
  },
  {
    "id": "sokani",
    "name": "Sokani",
    "district": "padaido"
  },
  {
    "id": "paidori",
    "name": "Paidori",
    "district": "padaido"
  }
]