[
  {
    "id": "pejengkolan",
    "name": "Pejengkolan",
    "district": "padureso"
  },
  {
    "id": "balingasal",
    "name": "Balingasal",
    "district": "padureso"
  },
  {
    "id": "kalijering",
    "name": "Kalijering",
    "district": "padureso"
  },
  {
    "id": "kaligubuk",
    "name": "Kaligubuk",
    "district": "padureso"
  },
  {
    "id": "sidototo",
    "name": "Sidototo",
    "district": "padureso"
  },
  {
    "id": "rahayu",
    "name": "Rahayu",
    "district": "padureso"
  },
  {
    "id": "sendangdalem",
    "name": "Sendangdalem",
    "district": "padureso"
  },
  {
    "id": "padureso",
    "name": "Padureso",
    "district": "padureso"
  }
]