[
  {
    "id": "kedaton",
    "name": "Kedaton",
    "district": "pagar-gunung"
  },
  {
    "id": "tanjung-agung",
    "name": "Tanjung Agung",
    "district": "pagar-gunung"
  },
  {
    "id": "pagar-agung",
    "name": "Pagar Agung",
    "district": "pagar-gunung"
  },
  {
    "id": "muara-dua",
    "name": "Muara Dua",
    "district": "pagar-gunung"
  },
  {
    "id": "penantian",
    "name": "Penantian",
    "district": "pagar-gunung"
  },
  {
    "id": "merindu",
    "name": "Merindu",
    "district": "pagar-gunung"
  },
  {
    "id": "gemidar-ulu",
    "name": "Gemidar Ulu",
    "district": "pagar-gunung"
  },
  {
    "id": "gemidar-ilir",
    "name": "Gemidar Ilir",
    "district": "pagar-gunung"
  },
  {
    "id": "rimba-sujud",
    "name": "Rimba Sujud",
    "district": "pagar-gunung"
  },
  {
    "id": "pagar-alam",
    "name": "Pagar Alam",
    "district": "pagar-gunung"
  },
  {
    "id": "padang-pagun",
    "name": "Padang Pagun",
    "district": "pagar-gunung"
  },
  {
    "id": "kupang",
    "name": "Kupang",
    "district": "pagar-gunung"
  },
  {
    "id": "danau",
    "name": "Danau",
    "district": "pagar-gunung"
  },
  {
    "id": "siring-agung",
    "name": "Siring Agung",
    "district": "pagar-gunung"
  },
  {
    "id": "batu-rusa",
    "name": "Batu Rusa",
    "district": "pagar-gunung"
  },
  {
    "id": "karang-agung",
    "name": "Karang Agung",
    "district": "pagar-gunung"
  },
  {
    "id": "sawah-darat",
    "name": "Sawah Darat",
    "district": "pagar-gunung"
  },
  {
    "id": "air-lingkar",
    "name": "Air Lingkar",
    "district": "pagar-gunung"
  },
  {
    "id": "lesung-batu",
    "name": "Lesung Batu",
    "district": "pagar-gunung"
  },
  {
    "id": "bandung-agung",
    "name": "Bandung Agung",
    "district": "pagar-gunung"
  }
]