[
  {
    "id": "lhok-puuk",
    "name": "Lhok Pu'Uk",
    "district": "panteraja"
  },
  {
    "id": "tunong",
    "name": "Tunong",
    "district": "panteraja"
  },
  {
    "id": "teungoh",
    "name": "Teungoh",
    "district": "panteraja"
  },
  {
    "id": "peurade",
    "name": "Peurade",
    "district": "panteraja"
  },
  {
    "id": "reudeup",
    "name": "Reudeup",
    "district": "panteraja"
  },
  {
    "id": "mesjid",
    "name": "Mesjid",
    "district": "panteraja"
  },
  {
    "id": "muka-blang",
    "name": "Muka Blang",
    "district": "panteraja"
  },
  {
    "id": "hagu",
    "name": "Hagu",
    "district": "panteraja"
  },
  {
    "id": "tu-pantee-raja",
    "name": "Tu Pantee Raja",
    "district": "panteraja"
  },
  {
    "id": "keude",
    "name": "Keude",
    "district": "panteraja"
  }
]