[
  {
    "id": "loa-deras",
    "name": "Loa Deras",
    "district": "penyinggahan"
  },
  {
    "id": "minta",
    "name": "Minta",
    "district": "penyinggahan"
  },
  {
    "id": "penyinggahan-ilir",
    "name": "Penyinggahan Ilir",
    "district": "penyinggahan"
  },
  {
    "id": "tanjung-haur",
    "name": "Tanjung Haur",
    "district": "penyinggahan"
  },
  {
    "id": "penyinggahan-ulu",
    "name": "Penyinggahan Ulu",
    "district": "penyinggahan"
  },
  {
    "id": "bakung",
    "name": "Bakung",
    "district": "penyinggahan"
  }
]