[
  {
    "id": "kumersot",
    "name": "Kumersot",
    "district": "ranowulu"
  },
  {
    "id": "pinokalan",
    "name": "Pinokalan",
    "district": "ranowulu"
  },
  {
    "id": "tewaan",
    "name": "Tewaan",
    "district": "ranowulu"
  },
  {
    "id": "danowudu",
    "name": "Danowudu",
    "district": "ranowulu"
  },
  {
    "id": "dua-sudara",
    "name": "Dua Sudara",
    "district": "ranowulu"
  },
  {
    "id": "apela-dua",
    "name": "Apela Dua",
    "district": "ranowulu"
  },
  {
    "id": "apela-satu",
    "name": "Apela Satu",
    "district": "ranowulu"
  },
  {
    "id": "karondoran",
    "name": "Karondoran",
    "district": "ranowulu"
  },
  {
    "id": "pinasungkulan",
    "name": "Pinasungkulan",
    "district": "ranowulu"
  },
  {
    "id": "batu-putih-atas",
    "name": "Batu Putih Atas",
    "district": "ranowulu"
  },
  {
    "id": "batu-putih-bawah",
    "name": "Batu Putih  Bawah",
    "district": "ranowulu"
  }
]