[
  {
    "id": "lawulo",
    "name": "Lawulo",
    "district": "samaturu"
  },
  {
    "id": "sani-sani",
    "name": "Sani Sani",
    "district": "samaturu"
  },
  {
    "id": "kaloloa",
    "name": "Kaloloa",
    "district": "samaturu"
  },
  {
    "id": "konaweha",
    "name": "Konaweha",
    "district": "samaturu"
  },
  {
    "id": "a-w-a",
    "name": "A W A",
    "district": "samaturu"
  },
  {
    "id": "lambolemo",
    "name": "Lambolemo",
    "district": "samaturu"
  },
  {
    "id": "tamboli",
    "name": "Tamboli",
    "district": "samaturu"
  },
  {
    "id": "tosiba",
    "name": "Tosiba",
    "district": "samaturu"
  },
  {
    "id": "amomutu",
    "name": "Amomutu",
    "district": "samaturu"
  },
  {
    "id": "malaha",
    "name": "Malaha",
    "district": "samaturu"
  },
  {
    "id": "latuo",
    "name": "Latuo",
    "district": "samaturu"
  },
  {
    "id": "wowa-tamboli",
    "name": "Wowa Tamboli",
    "district": "samaturu"
  },
  {
    "id": "tonganapo",
    "name": "Tonganapo",
    "district": "samaturu"
  },
  {
    "id": "ulu-konaweha",
    "name": "Ulu Konaweha",
    "district": "samaturu"
  },
  {
    "id": "puutamboli",
    "name": "Puutamboli",
    "district": "samaturu"
  },
  {
    "id": "puu-lawulo",
    "name": "Puu Lawulo",
    "district": "samaturu"
  },
  {
    "id": "liku",
    "name": "Liku",
    "district": "samaturu"
  },
  {
    "id": "meura",
    "name": "Meura",
    "district": "samaturu"
  },
  {
    "id": "ulaweng",
    "name": "Ulaweng",
    "district": "samaturu"
  }
]