[
  {
    "id": "sabuntan",
    "name": "Sabuntan",
    "district": "sapeken"
  },
  {
    "id": "paliat",
    "name": "Paliat",
    "district": "sapeken"
  },
  {
    "id": "sapeken",
    "name": "Sapeken",
    "district": "sapeken"
  },
  {
    "id": "sasiil",
    "name": "Sasiil",
    "district": "sapeken"
  },
  {
    "id": "sepanjang",
    "name": "Sepanjang",
    "district": "sapeken"
  },
  {
    "id": "tanjungkiaok",
    "name": "Tanjungkiaok",
    "district": "sapeken"
  },
  {
    "id": "pagerungan-kecil",
    "name": "Pagerungan Kecil",
    "district": "sapeken"
  },
  {
    "id": "pagerungan-besar",
    "name": "Pagerungan Besar",
    "district": "sapeken"
  },
  {
    "id": "sakala",
    "name": "Sakala",
    "district": "sapeken"
  },
  {
    "id": "sadulang",
    "name": "Sadulang",
    "district": "sapeken"
  },
  {
    "id": "saur-saebus",
    "name": "Saur Saebus",
    "district": "sapeken"
  }
]