[
  {
    "id": "seludau",
    "name": "Seludau",
    "district": "sesayap-hilir"
  },
  {
    "id": "sesayap",
    "name": "Sesayap",
    "district": "sesayap-hilir"
  },
  {
    "id": "sepala-dalung",
    "name": "Sepala Dalung",
    "district": "sesayap-hilir"
  },
  {
    "id": "bandan-bikis",
    "name": "Bandan Bikis",
    "district": "sesayap-hilir"
  },
  {
    "id": "bebatu",
    "name": "Bebatu",
    "district": "sesayap-hilir"
  },
  {
    "id": "sengkong",
    "name": "Sengkong",
    "district": "sesayap-hilir"
  },
  {
    "id": "sesayap-selor",
    "name": "Sesayap Selor",
    "district": "sesayap-hilir"
  }
]