[
  {
    "id": "betumonga",
    "name": "Betumonga",
    "district": "sipora-utara"
  },
  {
    "id": "goisooinan",
    "name": "Goisooinan",
    "district": "sipora-utara"
  },
  {
    "id": "bukit-pamewa",
    "name": "Bukit Pamewa",
    "district": "sipora-utara"
  },
  {
    "id": "sipora-jaya",
    "name": "Sipora Jaya",
    "district": "sipora-utara"
  },
  {
    "id": "sido-makmur",
    "name": "Sido Makmur",
    "district": "sipora-utara"
  },
  {
    "id": "tuapejat",
    "name": "Tuapejat",
    "district": "sipora-utara"
  }
]