[
  {
    "id": "tamba-dolok",
    "name": "Tamba Dolok",
    "district": "sitio-tio"
  },
  {
    "id": "cinta-maju",
    "name": "Cinta Maju",
    "district": "sitio-tio"
  },
  {
    "id": "buntu-mauli",
    "name": "Buntu Mauli",
    "district": "sitio-tio"
  },
  {
    "id": "sabulan",
    "name": "Sabulan",
    "district": "sitio-tio"
  },
  {
    "id": "holbung",
    "name": "Holbung",
    "district": "sitio-tio"
  },
  {
    "id": "janji-raja",
    "name": "Janji Raja",
    "district": "sitio-tio"
  },
  {
    "id": "janji-maria",
    "name": "Janji Maria",
    "district": "sitio-tio"
  },
  {
    "id": "parsaoran",
    "name": "Parsaoran",
    "district": "sitio-tio"
  }
]