[
  {
    "id": "cibeber",
    "name": "Cibeber",
    "district": "sukagumiwang"
  },
  {
    "id": "bondan",
    "name": "Bondan",
    "district": "sukagumiwang"
  },
  {
    "id": "gunungsari",
    "name": "Gunungsari",
    "district": "sukagumiwang"
  },
  {
    "id": "sukagumiwang",
    "name": "Sukagumiwang",
    "district": "sukagumiwang"
  },
  {
    "id": "tersana",
    "name": "Tersana",
    "district": "sukagumiwang"
  },
  {
    "id": "cadangpinggan",
    "name": "Cadangpinggan",
    "district": "sukagumiwang"
  },
  {
    "id": "gedangan",
    "name": "Gedangan",
    "district": "sukagumiwang"
  }
]