[
  {
    "id": "sukabumi-indah",
    "name": "Sukabumi Indah",
    "district": "sukabumi"
  },
  {
    "id": "sukabumi",
    "name": "Sukabumi",
    "district": "sukabumi"
  },
  {
    "id": "nusantara-permai",
    "name": "Nusantara Permai",
    "district": "sukabumi"
  },
  {
    "id": "campang-raya",
    "name": "Campang Raya",
    "district": "sukabumi"
  },
  {
    "id": "campang-jaya",
    "name": "Campang Jaya",
    "district": "sukabumi"
  },
  {
    "id": "way-gubak",
    "name": "Way Gubak",
    "district": "sukabumi"
  },
  {
    "id": "way-laga",
    "name": "Way Laga",
    "district": "sukabumi"
  },
  {
    "id": "parungseah",
    "name": "Parungseah",
    "district": "sukabumi"
  },
  {
    "id": "warnasari",
    "name": "Warnasari",
    "district": "sukabumi"
  },
  {
    "id": "sukajaya",
    "name": "Sukajaya",
    "district": "sukabumi"
  },
  {
    "id": "sudajaya-girang",
    "name": "Sudajaya Girang",
    "district": "sukabumi"
  },
  {
    "id": "karawang",
    "name": "Karawang",
    "district": "sukabumi"
  },
  {
    "id": "perbawati",
    "name": "Perbawati",
    "district": "sukabumi"
  }
]