[
  {
    "id": "oreng",
    "name": "Oreng",
    "district": "tanah-siang-selatan"
  },
  {
    "id": "olong-muro",
    "name": "Olong Muro",
    "district": "tanah-siang-selatan"
  },
  {
    "id": "olong-hanangan",
    "name": "Olong Hanangan",
    "district": "tanah-siang-selatan"
  },
  {
    "id": "dirung-lingkin",
    "name": "Dirung Lingkin",
    "district": "tanah-siang-selatan"
  },
  {
    "id": "datah-kotou",
    "name": "Datah Kotou",
    "district": "tanah-siang-selatan"
  },
  {
    "id": "tahujan-ontu",
    "name": "Tahujan Ontu",
    "district": "tanah-siang-selatan"
  }
]