[
  {
    "id": "tanjung-balai-kota-iii",
    "name": "Tanjung Balai Kota  Iii",
    "district": "tanjung-balai-utara"
  },
  {
    "id": "mata-halasan",
    "name": "Mata Halasan",
    "district": "tanjung-balai-utara"
  },
  {
    "id": "kwala-silau-bestari",
    "name": "Kwala Silau Bestari",
    "district": "tanjung-balai-utara"
  },
  {
    "id": "tanjung-balai-kota-iv",
    "name": "Tanjung Balai Kota Iv",
    "district": "tanjung-balai-utara"
  },
  {
    "id": "sejahtera",
    "name": "Sejahtera",
    "district": "tanjung-balai-utara"
  }
]