[
  {
    "id": "kapias-batu-viii",
    "name": "Kapias Batu Viii",
    "district": "tanjung-balai"
  },
  {
    "id": "pematang-sungai-baru",
    "name": "Pematang Sungai Baru",
    "district": "tanjung-balai"
  },
  {
    "id": "sei-apung-jaya",
    "name": "Sei Apung Jaya",
    "district": "tanjung-balai"
  },
  {
    "id": "sungai-apung",
    "name": "Sungai Apung",
    "district": "tanjung-balai"
  },
  {
    "id": "asahan-mati",
    "name": "Asahan Mati",
    "district": "tanjung-balai"
  },
  {
    "id": "bagan-asahan-baru",
    "name": "Bagan Asahan Baru",
    "district": "tanjung-balai"
  },
  {
    "id": "bagan-asahan-pekan",
    "name": "Bagan Asahan Pekan",
    "district": "tanjung-balai"
  },
  {
    "id": "bagan-asahan",
    "name": "Bagan Asahan",
    "district": "tanjung-balai"
  }
]