[
  {
    "id": "mamburungan",
    "name": "Mamburungan",
    "district": "tarakan-timur"
  },
  {
    "id": "mamburungan-timur",
    "name": "Mamburungan Timur",
    "district": "tarakan-timur"
  },
  {
    "id": "pantai-amal",
    "name": "Pantai Amal",
    "district": "tarakan-timur"
  },
  {
    "id": "kampung-enam",
    "name": "Kampung Enam",
    "district": "tarakan-timur"
  },
  {
    "id": "kampung-empat",
    "name": "Kampung Empat",
    "district": "tarakan-timur"
  },
  {
    "id": "gunung-lingkas",
    "name": "Gunung Lingkas",
    "district": "tarakan-timur"
  },
  {
    "id": "lingkas-ujung",
    "name": "Lingkas Ujung",
    "district": "tarakan-timur"
  }
]