[
  {
    "id": "batu-menyan",
    "name": "Batu Menyan",
    "district": "teluk-pandan"
  },
  {
    "id": "gebang",
    "name": "Gebang",
    "district": "teluk-pandan"
  },
  {
    "id": "sidodadi",
    "name": "Sidodadi",
    "district": "teluk-pandan"
  },
  {
    "id": "hanura",
    "name": "Hanura",
    "district": "teluk-pandan"
  },
  {
    "id": "cilimus",
    "name": "Cilimus",
    "district": "teluk-pandan"
  },
  {
    "id": "hurun",
    "name": "Hurun",
    "district": "teluk-pandan"
  },
  {
    "id": "sukajaya-lempasing",
    "name": "Sukajaya Lempasing",
    "district": "teluk-pandan"
  },
  {
    "id": "munca",
    "name": "Munca",
    "district": "teluk-pandan"
  },
  {
    "id": "tanjung-agung",
    "name": "Tanjung Agung",
    "district": "teluk-pandan"
  },
  {
    "id": "talang-mulyo",
    "name": "Talang Mulyo",
    "district": "teluk-pandan"
  },
  {
    "id": "teluk-pandan",
    "name": "Teluk Pandan",
    "district": "teluk-pandan"
  },
  {
    "id": "suka-damai",
    "name": "Suka Damai",
    "district": "teluk-pandan"
  },
  {
    "id": "suka-rahmat",
    "name": "Suka Rahmat",
    "district": "teluk-pandan"
  },
  {
    "id": "danau-redan",
    "name": "Danau Redan",
    "district": "teluk-pandan"
  },
  {
    "id": "martadinata",
    "name": "Martadinata",
    "district": "teluk-pandan"
  },
  {
    "id": "kandolo",
    "name": "Kandolo",
    "district": "teluk-pandan"
  }
]