[
  {
    "id": "sital",
    "name": "Sital",
    "district": "teupah-barat"
  },
  {
    "id": "leubang",
    "name": "Leubang",
    "district": "teupah-barat"
  },
  {
    "id": "leubang-hulu",
    "name": "Leubang Hulu",
    "district": "teupah-barat"
  },
  {
    "id": "awe-seubal",
    "name": "Awe Seubal",
    "district": "teupah-barat"
  },
  {
    "id": "lantik",
    "name": "Lantik",
    "district": "teupah-barat"
  },
  {
    "id": "awe-kecil",
    "name": "Awe Kecil",
    "district": "teupah-barat"
  },
  {
    "id": "salur",
    "name": "Salur",
    "district": "teupah-barat"
  },
  {
    "id": "salur-latun",
    "name": "Salur Latun",
    "district": "teupah-barat"
  },
  {
    "id": "salur-lasengalu",
    "name": "Salur Lasengalu",
    "district": "teupah-barat"
  },
  {
    "id": "nancala",
    "name": "Nancala",
    "district": "teupah-barat"
  },
  {
    "id": "maudil",
    "name": "Maudil",
    "district": "teupah-barat"
  },
  {
    "id": "inor",
    "name": "Inor",
    "district": "teupah-barat"
  },
  {
    "id": "naibos",
    "name": "Naibos",
    "district": "teupah-barat"
  },
  {
    "id": "laayon",
    "name": "Laayon",
    "district": "teupah-barat"
  },
  {
    "id": "angkeo",
    "name": "Angkeo",
    "district": "teupah-barat"
  },
  {
    "id": "bunon",
    "name": "Bunon",
    "district": "teupah-barat"
  },
  {
    "id": "silengas",
    "name": "Silengas",
    "district": "teupah-barat"
  },
  {
    "id": "pulau-teupah",
    "name": "Pulau Teupah",
    "district": "teupah-barat"
  }
]