[
  {
    "id": "sarerangan",
    "name": "Sarerangan",
    "district": "tewah"
  },
  {
    "id": "tumbang-pajangei",
    "name": "Tumbang Pajangei",
    "district": "tewah"
  },
  {
    "id": "sumur-mas",
    "name": "Sumur Mas",
    "district": "tewah"
  },
  {
    "id": "tewah",
    "name": "Tewah",
    "district": "tewah"
  },
  {
    "id": "kasintu",
    "name": "Kasintu",
    "district": "tewah"
  },
  {
    "id": "upon-batu",
    "name": "Upon Batu",
    "district": "tewah"
  },
  {
    "id": "batu-nyiwuh",
    "name": "Batu Nyiwuh",
    "district": "tewah"
  },
  {
    "id": "tumbang-habaon",
    "name": "Tumbang Habaon",
    "district": "tewah"
  },
  {
    "id": "tanjung-untung",
    "name": "Tanjung Untung",
    "district": "tewah"
  },
  {
    "id": "sandung-tambun",
    "name": "Sandung Tambun",
    "district": "tewah"
  },
  {
    "id": "sei-riang",
    "name": "Sei Riang",
    "district": "tewah"
  },
  {
    "id": "batu-nyapau",
    "name": "Batu  Nyapau",
    "district": "tewah"
  },
  {
    "id": "rangan-mihing",
    "name": "Rangan Mihing",
    "district": "tewah"
  },
  {
    "id": "teluk-lawah",
    "name": "Teluk Lawah",
    "district": "tewah"
  },
  {
    "id": "taja-urap",
    "name": "Taja Urap",
    "district": "tewah"
  },
  {
    "id": "karason",
    "name": "Karason",
    "district": "tewah"
  }
]