[
  {
    "id": "panyipatan",
    "name": "Panyipatan",
    "regency": "kabupaten-tanah-laut"
  },
  {
    "id": "takisung",
    "name": "Takisung",
    "regency": "kabupaten-tanah-laut"
  },
  {
    "id": "kurau",
    "name": "Kurau",
    "regency": "kabupaten-tanah-laut"
  },
  {
    "id": "bumi-makmur",
    "name": "Bumi Makmur",
    "regency": "kabupaten-tanah-laut"
  },
  {
    "id": "bati-bati",
    "name": "Bati - Bati",
    "regency": "kabupaten-tanah-laut"
  },
  {
    "id": "tambang-ulang",
    "name": "Tambang Ulang",
    "regency": "kabupaten-tanah-laut"
  },
  {
    "id": "pelaihari",
    "name": "Pelaihari",
    "regency": "kabupaten-tanah-laut"
  },
  {
    "id": "bajuin",
    "name": "Bajuin",
    "regency": "kabupaten-tanah-laut"
  },
  {
    "id": "batu-ampar",
    "name": "Batu Ampar",
    "regency": "kabupaten-tanah-laut"
  },
  {
    "id": "jorong",
    "name": "Jorong",
    "regency": "kabupaten-tanah-laut"
  },
  {
    "id": "kintap",
    "name": "Kintap",
    "regency": "kabupaten-tanah-laut"
  }
]