[
  {
    "id": "ciwandan",
    "name": "Ciwandan",
    "regency": "kota-cilegon"
  },
  {
    "id": "citangkil",
    "name": "Citangkil",
    "regency": "kota-cilegon"
  },
  {
    "id": "pulomerak",
    "name": "Pulomerak",
    "regency": "kota-cilegon"
  },
  {
    "id": "purwakarta",
    "name": "Purwakarta",
    "regency": "kota-cilegon"
  },
  {
    "id": "grogol",
    "name": "Grogol",
    "regency": "kota-cilegon"
  },
  {
    "id": "cilegon",
    "name": "Cilegon",
    "regency": "kota-cilegon"
  },
  {
    "id": "jombang",
    "name": "Jombang",
    "regency": "kota-cilegon"
  },
  {
    "id": "cibeber",
    "name": "Cibeber",
    "regency": "kota-cilegon"
  }
]